README.txt
setup.py
Products/__init__.py
Products.PloneInvite.egg-info/PKG-INFO
Products.PloneInvite.egg-info/SOURCES.txt
Products.PloneInvite.egg-info/dependency_links.txt
Products.PloneInvite.egg-info/entry_points.txt
Products.PloneInvite.egg-info/namespace_packages.txt
Products.PloneInvite.egg-info/not-zip-safe
Products.PloneInvite.egg-info/requires.txt
Products.PloneInvite.egg-info/top_level.txt
Products/PloneInvite/LICENSE.TXT
Products/PloneInvite/Makefile
Products/PloneInvite/Permissions.py
Products/PloneInvite/PloneInvite.py
Products/PloneInvite/TRANSLATING.txt
Products/PloneInvite/__init__.py
Products/PloneInvite/config.py
Products/PloneInvite/fakemessagefactory.py
Products/PloneInvite/refresh.txt
Products/PloneInvite/tool.gif
Products/PloneInvite/version.txt
Products/PloneInvite/Extensions/Install.py
Products/PloneInvite/Extensions/__init__.py
Products/PloneInvite/dtml/invite.dtml
Products/PloneInvite/dtml/overview.dtml
Products/PloneInvite/i18n/PloneInvite-de.po
Products/PloneInvite/i18n/PloneInvite-es.po
Products/PloneInvite/i18n/PloneInvite-nl.po
Products/PloneInvite/i18n/PloneInvite.pot
Products/PloneInvite/i18n/base.pot
Products/PloneInvite/i18n/plone-de.po
Products/PloneInvite/i18n/plone-es.po
Products/PloneInvite/i18n/plone-nl.po
Products/PloneInvite/i18n/plone.pot
Products/PloneInvite/skins/ploneinvite/delete_invite_codes.cpy
Products/PloneInvite/skins/ploneinvite/delete_invite_codes.cpy.metadata
Products/PloneInvite/skins/ploneinvite/get_portal_invite_ftests.py
Products/PloneInvite/skins/ploneinvite/invite.cpy
Products/PloneInvite/skins/ploneinvite/invite.cpy.metadata
Products/PloneInvite/skins/ploneinvite/invite_form.cpt
Products/PloneInvite/skins/ploneinvite/invite_form.cpt.metadata
Products/PloneInvite/skins/ploneinvite/invite_stat.pt
Products/PloneInvite/skins/ploneinvite/invite_template.pt
Products/PloneInvite/skins/ploneinvite/invites_form.cpt
Products/PloneInvite/skins/ploneinvite/invites_form.cpt.metadata
Products/PloneInvite/skins/ploneinvite/join_form.cpt
Products/PloneInvite/skins/ploneinvite/join_form.cpt.metadata
Products/PloneInvite/skins/ploneinvite/register.cpy
Products/PloneInvite/skins/ploneinvite/register.cpy.metadata
Products/PloneInvite/skins/ploneinvite/send_invite_codes.cpy
Products/PloneInvite/skins/ploneinvite/send_invite_codes.cpy.metadata
