Metadata-Version: 1.0
Name: Products.PloneInvite
Version: 1.1.6
Summary: Members can invite new members; registration only possible if invited
Home-page: http://plone.org/products/plone-invite/
Author: Kees Hink
Author-email: hink@gw20e.com
License: GPL
Keywords: Plone PloneInvite
Platform: UNKNOWN
Classifier: Programming Language :: Python
Classifier: Topic :: Software Development :: Libraries :: Python Modules
Classifier: Framework :: Plone
